testudo/__init__.py
testudo/cli.py
testudo/config.py
testudo/log.py
testudo/reporter.py
testudo/runner.py
testudo/task_manager.py
testudo-0.3.2.dist-info/entry_points.txt
testudo-0.3.2.dist-info/WHEEL
testudo-0.3.2.dist-info/METADATA
testudo-0.3.2.dist-info/licenses/LICENSE
testudo-0.3.2.dist-info/RECORD
