Metadata-Version: 2.1
Name: testudo
Version: 0.3.2
Summary: A wrapper for commands to be run as periodic tasks while reporting on their results/errors to legiond. Intended to be integrated with supervisord, should work well with systemd in theory.
License: GPL-3.0-or-later
Author-email: Eugene Kovalev <eugene@kovalev.systems>
Requires-Python: >=3.8.3,<4.0
Requires-Dist: click<9.0.0,>=8.0.3
Requires-Dist: legion-utils<1.0.0,>=0.3.2
